radix4_booth_multiplier/rtl/Booth_decoder.v
module Booth_decoder #(
    parameter WIDTH = 32
)(
    input  wire [(WIDTH/2)*3 - 1 : 0] seq_in, 
    input  wire [WIDTH-1:0] M,               

    output reg  [(WIDTH/2)*(WIDTH+1) - 1 : 0] extended_out, 
    output reg  [WIDTH/2 - 1 : 0] sgn_out,                  
    output reg  [WIDTH/2 - 1 : 0] e_out                     
);

    localparam NUM_SEQ = WIDTH / 2;     
    localparam PP_WIDTH = WIDTH + 1;    

    wire multiplicand_sign = M[WIDTH-1];

    integer i;
    reg [2:0] seq;

    always @(*) begin
        for (i = 0; i < NUM_SEQ; i = i + 1) begin
            // Đã fix: Dùng Indexed Part Select (+:) để cắt 3 bit
            seq = seq_in[i*3 +: 3];

            case (seq)
                3'b000, 3'b111: begin
                    extended_out[i*PP_WIDTH +: PP_WIDTH] = {PP_WIDTH{1'b0}};
                    sgn_out[i] = 0; 
                    e_out[i]   = 1;
                end
                
                3'b001, 3'b010: begin // +1M
                    extended_out[i*PP_WIDTH +: PP_WIDTH] = {M[WIDTH-1], M}; 
                    sgn_out[i] = 0;
                    e_out[i]   = ~(multiplicand_sign ^ 1'b0);
                end
                
                3'b011: begin // +2M
                    extended_out[i*PP_WIDTH +: PP_WIDTH] = {M, 1'b0}; 
                    sgn_out[i] = 0;
                    e_out[i]   = ~(multiplicand_sign ^ 1'b0);
                end
                
                3'b100: begin // -2M
                    extended_out[i*PP_WIDTH +: PP_WIDTH] = ~{M, 1'b0}; 
                    sgn_out[i] = 1;
                    e_out[i]   = ~(multiplicand_sign ^ 1'b1);
                end
                
                3'b101, 3'b110: begin // -1M
                    extended_out[i*PP_WIDTH +: PP_WIDTH] = ~{M[WIDTH-1], M}; 
                    sgn_out[i] = 1;
                    e_out[i]   = ~(multiplicand_sign ^ 1'b1);
                end
                
                default: begin
                    extended_out[i*PP_WIDTH +: PP_WIDTH] = {PP_WIDTH{1'b0}};
                    sgn_out[i] = 0;
                    e_out[i]   = 1;
                end
            endcase
        end
    end

endmodule

radix4_booth_multiplier/rtl/Booth_encoder.v
module Booth_encoder #(parameter WIDTH = 32
)(
    input wire [WIDTH-1:0] Q,
    output wire [(WIDTH/2)*3-1:0] seq_out
);

wire [WIDTH:0] extended_Q = {Q, 1'b0}; //extended to 33bits (32bit A + 1bit LSB)

//extract sequences
genvar i;
generate
    for (i=0; i<(WIDTH/2); i = i + 1) //16 pp generator
    begin
        assign seq_out[i*3 + 2 : i*3] = extended_Q[i*2 + 2 : i*2];
    end
endgenerate

endmodule

radix4_booth_multiplier/rtl/radix4_Booth_mul.v
module radix4_Booth_mul(
    input  wire [31:0] M,
    input  wire [31:0] Q,
    output wire [63:0] P
);

    wire [47:0] seq_in; 
    wire [527:0] extended_out; 
    wire [15:0] sgn_out;
    wire [15:0] e_out;

    // Gọi Encoder
    Booth_encoder #(32) enc(
        .Q(Q),
        .seq_out(seq_in)
    );

    // Gọi Decoder
    Booth_decoder #(32) dec(
        .seq_in(seq_in),
        .M(M),
        .extended_out(extended_out),
        .sgn_out(sgn_out),
        .e_out(e_out)
    );

    reg [64:0] layers [0:16]; 
    reg [64:0] final_sum;

    integer i;
    always @(*) begin
        for (i = 0; i < 17; i = i + 1) begin
            layers[i] = 65'b0;
        end

        for (i = 0; i < 16; i = i + 1) begin
            // Nạp 33-bit Partial Product
            layers[i][2*i +: 33] = extended_out[i*33 +: 33];

            if (i == 0) begin
                // ĐÃ FIX BUGS: Đảo lại thứ tự thành ~e, ~e, e 
                layers[0][33] = ~e_out[0];
                layers[0][34] = ~e_out[0];
                layers[0][35] = e_out[0];
            end else begin
                // Các hàng dưới giữ nguyên
                layers[i][2*i + 33] = e_out[i];
                layers[i][2*i + 34] = 1'b1;
                // Ký gửi bit sgn
                layers[i][2*i - 2] = sgn_out[i-1];
            end
        end

        // Bit sgn cuối cùng của hàng 16
        layers[16][30] = sgn_out[15];

        // Nén song song
        final_sum = 65'b0;
        for (i = 0; i < 17; i = i + 1) begin
            final_sum = final_sum + layers[i];
        end
    end

    assign P = final_sum[63:0];

endmodule

radix4_booth_multiplier/tb/test_bench.v
`timescale 1ns / 1ps

module test_bench;
    reg [31:0] M;
    reg [31:0] Q;
    wire [63:0] P;
    
//internal signals
reg [63:0] expected_P;
integer i;
integer error_count;
reg clk;

radix4_Booth_mul dut (
    .M(M),
    .Q(Q),
    .P(P)
);

initial begin
    clk = 0;
end

always #5 clk = ~clk;

initial begin
    $dumpfile("wave.vcd");
    $dumpvars(0, test_bench);
    
    M = 32'd0;
    Q = 32'd0;
    error_count = 0;
    $display("==========================================");
    $display("TESTING 32-BIT RADIX-4 BOOTH MULTIPLIER...");
    $display("==========================================");
    
    //Checkerboard
    $display("\n Coner testcases...");
    test_mul(32'hFFFF_FFFF, 32'hFFFF_FFFF);
    test_mul(32'hAAAA_AAAA, 32'h5555_5555);
    test_mul(32'h1111_1111, 32'hBCBC_BCBC);
    
    //Boundaries
    test_mul(32'h8000_0000, 32'h8000_0000);
    test_mul(32'h7FFF_FFFF, 32'h7FFF_FFFF);
    test_mul(32'h7FFF_FFFF, 32'h8000_0000);
    
    test_mul(32'h0000_0000, 32'h0000_0000);
    test_mul(32'h1234_5678, 32'h0000_0000);
    test_mul(32'h8000_0000, 32'h0000_0001);
    test_mul(32'h7FFF_FFFF, 32'hFFFF_FFFF);

    //Asymetric
    test_mul(32'h0000_0003, 32'h7FFF_FFF3);
    test_mul(32'hFFFF_FFFD, 32'h0000_0005);


    //Random test
    $display("\n Random testcases...");
    for (i=0; i<100; i = i + 1) begin
        test_mul($random, $random);
    end
    
    $display("==================================================");
    if (error_count == 0) begin
    $display("[SUCCESS]: PASS ALL TESTCASES");
    $display("--- SIMULATION FINISHED ---");
    end else begin
    $display("[FAIL]: FAIL %0d TESTCASES COUNT", error_count);
    $display("--- SIMULATION FINISHED ---");
    end
    $display("==================================================");
        
    #100; 
    $finish;
end

task test_mul;
    input [31:0] test_M;
    input [31:0] test_Q;

begin
    @(posedge clk);
    #1;
    M = test_M;
    Q = test_Q;

    //golden model
    expected_P = $signed(test_M) * $signed(test_Q);
    #10;

    if (P !== expected_P) begin
        $display("[FAIL] Time: %0t | M = %h | Q = %h | P = %h | exp_P = %h", $time, M, Q, P, expected_P);
        error_count = error_count + 1;
    end else begin
        $display("[PASS] Time: %0t | M = %h | Q = %h | P = %h | exp_P = %h", $time, M, Q, P, expected_P);
    end
end
endtask

endmodule

radix4_booth_multiplier/sim/wave.vcd
$date
	Tue Jun  2 13:49:22 2026
$end
$version
	Icarus Verilog
$end
$timescale
	1ps
$end
$scope module test_bench $end
$var wire 64 ! P [63:0] $end
$var reg 32 " M [31:0] $end
$var reg 32 # Q [31:0] $end
$var reg 1 $ clk $end
$var reg 64 % expected_P [63:0] $end
$var integer 32 & error_count [31:0] $end
$var integer 32 ' i [31:0] $end
$scope module dut $end
$var wire 32 ( M [31:0] $end
$var wire 32 ) Q [31:0] $end
$var wire 16 * sgn_out [15:0] $end
$var wire 48 + seq_in [47:0] $end
$var wire 528 , extended_out [527:0] $end
$var wire 16 - e_out [15:0] $end
$var wire 64 . P [63:0] $end
$var reg 65 / final_sum [64:0] $end
$var integer 32 0 i [31:0] $end
$scope module dec $end
$var wire 32 1 M [31:0] $end
$var wire 48 2 seq_in [47:0] $end
$var wire 1 3 multiplicand_sign $end
$var parameter 32 4 NUM_SEQ $end
$var parameter 33 5 PP_WIDTH $end
$var parameter 32 6 WIDTH $end
$var reg 16 7 e_out [15:0] $end
$var reg 528 8 extended_out [527:0] $end
$var reg 3 9 seq [2:0] $end
$var reg 16 : sgn_out [15:0] $end
$var integer 32 ; i [31:0] $end
$upscope $end
$scope module enc $end
$var wire 32 < Q [31:0] $end
$var wire 48 = seq_out [47:0] $end
$var wire 33 > extended_Q [32:0] $end
$var parameter 32 ? WIDTH $end
$scope begin genblk1[0] $end
$var parameter 2 @ i $end
$upscope $end
$scope begin genblk1[1] $end
$var parameter 2 A i $end
$upscope $end
$scope begin genblk1[2] $end
$var parameter 3 B i $end
$upscope $end
$scope begin genblk1[3] $end
$var parameter 3 C i $end
$upscope $end
$scope begin genblk1[4] $end
$var parameter 4 D i $end
$upscope $end
$scope begin genblk1[5] $end
$var parameter 4 E i $end
$upscope $end
$scope begin genblk1[6] $end
$var parameter 4 F i $end
$upscope $end
$scope begin genblk1[7] $end
$var parameter 4 G i $end
$upscope $end
$scope begin genblk1[8] $end
$var parameter 5 H i $end
$upscope $end
$scope begin genblk1[9] $end
$var parameter 5 I i $end
$upscope $end
$scope begin genblk1[10] $end
$var parameter 5 J i $end
$upscope $end
$scope begin genblk1[11] $end
$var parameter 5 K i $end
$upscope $end
$scope begin genblk1[12] $end
$var parameter 5 L i $end
$upscope $end
$scope begin genblk1[13] $end
$var parameter 5 M i $end
$upscope $end
$scope begin genblk1[14] $end
$var parameter 5 N i $end
$upscope $end
$scope begin genblk1[15] $end
$var parameter 5 O i $end
$upscope $end
$upscope $end
$upscope $end
$scope task test_mul $end
$var reg 32 P test_M [31:0] $end
$var reg 32 Q test_Q [31:0] $end
$upscope $end
$upscope $end
$enddefinitions $end
$comment Show the parameter values. $end
$dumpall
b1111 O
b1110 N
b1101 M
b1100 L
b1011 K
b1010 J
b1001 I
b1000 H
b111 G
b110 F
b101 E
b100 D
b11 C
b10 B
b1 A
b0 @
b100000 ?
b100000 6
b100001 5
b10000 4
$end
#0
$dumpvars
b11111111111111111111111111111111 Q
b11111111111111111111111111111111 P
b0 >
b0 =
b0 <
b10000 ;
b0 :
b0 9
b0 8
b1111111111111111 7
03
b0 2
b0 1
b10001 0
b0 /
b0 .
b1111111111111111 -
b0 ,
b0 +
b0 *
b0 )
b0 (
bx '
b0 &
bx %
0$
b0 #
b0 "
b0 !
$end
#5000
1$
#6000
b1 !
b1 .
b1 /
b10001 0
b1 *
b1 :
b111 9
b111111111111111111111111111111111111111111111110 +
b111111111111111111111111111111111111111111111110 2
b111111111111111111111111111111111111111111111110 =
b10000 ;
13
b1 %
b111111111111111111111111111111110 >
b11111111111111111111111111111111 #
b11111111111111111111111111111111 )
b11111111111111111111111111111111 <
b11111111111111111111111111111111 "
b11111111111111111111111111111111 (
b11111111111111111111111111111111 1
#10000
0$
#15000
1$
#16000
b1010101010101010101010101010101 Q
b10101010101010101010101010101010 P
#20000
0$
#25000
1$
#26000
b1110001110001110001110001110001101110001110001110001110001110010 !
b1110001110001110001110001110001101110001110001110001110001110010 .
b0 -
b0 7
b0 *
b0 :
b11110001110001110001110001110001101110001110001110001110001110010 /
b10001 0
b10010010010010010010010010010010010010010010010 +
b10010010010010010010010010010010010010010010010 2
b10010010010010010010010010010010010010010010010 =
b110101010101010101010101010101010110101010101010101010101010101010110101010101010101010101010101010110101010101010101010101010101010110101010101010101010101010101010110101010101010101010101010101010110101010101010101010101010101010110101010101010101010101010101010110101010101010101010101010101010110101010101010101010101010101010110101010101010101010101010101010110101010101010101010101010101010110101010101010101010101010101010110101010101010101010101010101010110101010101010101010101010101010110101010101010101010101010101010 ,
b110101010101010101010101010101010110101010101010101010101010101010110101010101010101010101010101010110101010101010101010101010101010110101010101010101010101010101010110101010101010101010101010101010110101010101010101010101010101010110101010101010101010101010101010110101010101010101010101010101010110101010101010101010101010101010110101010101010101010101010101010110101010101010101010101010101010110101010101010101010101010101010110101010101010101010101010101010110101010101010101010101010101010110101010101010101010101010101010 8
b10 9
b10000 ;
b1110001110001110001110001110001101110001110001110001110001110010 %
b10101010101010101010101010101010 >
b1010101010101010101010101010101 #
b1010101010101010101010101010101 )
b1010101010101010101010101010101 <
b10101010101010101010101010101010 "
b10101010101010101010101010101010 (
b10101010101010101010101010101010 1
#30000
0$
#35000
1$
#36000
b10111100101111001011110010111100 Q
b10001000100010001000100010001 P
#40000
0$
#45000
1$
#46000
b1111101110000100000011001001010100010101100011010000010001111100 !
b1111101110000100000011001001010100010101100011010000010001111100 .
b1010101010101010 *
b1010101010101010 :
b101 9
b11111101110000100000011001001010100010101100011010000010001111100 /
b10001 0
b101111110001101111110001101111110001101111110000 +
b101111110001101111110001101111110001101111110000 2
b101111110001101111110001101111110001101111110000 =
b101010101010101 -
b101010101010101 7
b111101110111011101110111011101110000000000000000000000000000000000111101110111011101110111011101110000010001000100010001000100010001111101110111011101110111011101110000000000000000000000000000000000111101110111011101110111011101110000010001000100010001000100010001111101110111011101110111011101110000000000000000000000000000000000111101110111011101110111011101110000010001000100010001000100010001111101110111011101110111011101110000000000000000000000000000000000111101110111011101110111011101110000000000000000000000000000000000 ,
b111101110111011101110111011101110000000000000000000000000000000000111101110111011101110111011101110000010001000100010001000100010001111101110111011101110111011101110000000000000000000000000000000000111101110111011101110111011101110000010001000100010001000100010001111101110111011101110111011101110000000000000000000000000000000000111101110111011101110111011101110000010001000100010001000100010001111101110111011101110111011101110000000000000000000000000000000000111101110111011101110111011101110000000000000000000000000000000000 8
b10000 ;
03
b1111101110000100000011001001010100010101100011010000010001111100 %
b101111001011110010111100101111000 >
b10111100101111001011110010111100 #
b10111100101111001011110010111100 )
b10111100101111001011110010111100 <
b10001000100010001000100010001 "
b10001000100010001000100010001 (
b10001000100010001000100010001 1
#50000
0$
#55000
1$
#56000
b10000000000000000000000000000000 Q
b10000000000000000000000000000000 P
#60000
0$
#65000
1$
#66000
b100000000000000000000000000000000000000000000000000000000000000 !
b100000000000000000000000000000000000000000000000000000000000000 .
b1000000000000000 *
b1000000000000000 :
b100000000000000000000000000000000000000000000000000000000000000 /
b10001 0
b100000000000000000000000000000000000000000000000 +
b100000000000000000000000000000000000000000000000 2
b100000000000000000000000000000000000000000000000 =
b1111111111111111 -
b1111111111111111 7
b11111111111111111111111111111111000000000000000000000000000000000000000000000000000000000000000000000000000000000000000000000000000000000000000000000000000000000000000000000000000000000000000000000000000000000000000000000000000000000000000000000000000000000000000000000000000000000000000000000000000000000000000000000000000000000000000000000000000000000000000000000000000000000000000000000000000000000000000000000000000000000000000000000000000000000000000000000000000000000000000000000000000000000000000000000000000000000000000 ,
b11111111111111111111111111111111000000000000000000000000000000000000000000000000000000000000000000000000000000000000000000000000000000000000000000000000000000000000000000000000000000000000000000000000000000000000000000000000000000000000000000000000000000000000000000000000000000000000000000000000000000000000000000000000000000000000000000000000000000000000000000000000000000000000000000000000000000000000000000000000000000000000000000000000000000000000000000000000000000000000000000000000000000000000000000000000000000000000000 8
b100 9
b10000 ;
13
b100000000000000000000000000000000000000000000000000000000000000 %
b100000000000000000000000000000000 >
b10000000000000000000000000000000 #
b10000000000000000000000000000000 )
b10000000000000000000000000000000 <
b10000000000000000000000000000000 "
b10000000000000000000000000000000 (
b10000000000000000000000000000000 1
#70000
0$
#75000
1$
#76000
b1111111111111111111111111111111 Q
b1111111111111111111111111111111 P
#80000
0$
#85000
1$
#86000
b11111111111111111111111111111100000000000000000000000000000001 !
b11111111111111111111111111111100000000000000000000000000000001 .
b1 *
b1 :
b11111111111111111111111111111100000000000000000000000000000001 /
b10001 0
b11111111111111111111111111111111111111111111110 +
b11111111111111111111111111111111111111111111110 2
b11111111111111111111111111111111111111111111110 =
b1111111111111110 -
b1111111111111110 7
b11111111111111111111111111111110000000000000000000000000000000000000000000000000000000000000000000000000000000000000000000000000000000000000000000000000000000000000000000000000000000000000000000000000000000000000000000000000000000000000000000000000000000000000000000000000000000000000000000000000000000000000000000000000000000000000000000000000000000000000000000000000000000000000000000000000000000000000000000000000000000000000000000000000000000000000000000000000000000000000000000000000000000110000000000000000000000000000000 ,
b11111111111111111111111111111110000000000000000000000000000000000000000000000000000000000000000000000000000000000000000000000000000000000000000000000000000000000000000000000000000000000000000000000000000000000000000000000000000000000000000000000000000000000000000000000000000000000000000000000000000000000000000000000000000000000000000000000000000000000000000000000000000000000000000000000000000000000000000000000000000000000000000000000000000000000000000000000000000000000000000000000000000000110000000000000000000000000000000 8
b11 9
b10000 ;
03
b11111111111111111111111111111100000000000000000000000000000001 %
b11111111111111111111111111111110 >
b1111111111111111111111111111111 #
b1111111111111111111111111111111 )
b1111111111111111111111111111111 <
b1111111111111111111111111111111 "
b1111111111111111111111111111111 (
b1111111111111111111111111111111 1
#90000
0$
#95000
1$
#96000
b10000000000000000000000000000000 Q
#100000
0$
#105000
1$
#106000
b1100000000000000000000000000000010000000000000000000000000000000 !
b1100000000000000000000000000000010000000000000000000000000000000 .
b11100000000000000000000000000000010000000000000000000000000000000 /
b10001 0
b111111111111111 -
b111111111111111 7
b1000000000000000 *
b1000000000000000 :
b100000000000000000000000000000001000000000000000000000000000000000000000000000000000000000000000000000000000000000000000000000000000000000000000000000000000000000000000000000000000000000000000000000000000000000000000000000000000000000000000000000000000000000000000000000000000000000000000000000000000000000000000000000000000000000000000000000000000000000000000000000000000000000000000000000000000000000000000000000000000000000000000000000000000000000000000000000000000000000000000000000000000000000000000000000000000000000000000 ,
b100000000000000000000000000000001000000000000000000000000000000000000000000000000000000000000000000000000000000000000000000000000000000000000000000000000000000000000000000000000000000000000000000000000000000000000000000000000000000000000000000000000000000000000000000000000000000000000000000000000000000000000000000000000000000000000000000000000000000000000000000000000000000000000000000000000000000000000000000000000000000000000000000000000000000000000000000000000000000000000000000000000000000000000000000000000000000000000000 8
b100 9
b10000 ;
b100000000000000000000000000000000000000000000000 +
b100000000000000000000000000000000000000000000000 2
b100000000000000000000000000000000000000000000000 =
b1100000000000000000000000000000010000000000000000000000000000000 %
b100000000000000000000000000000000 >
b10000000000000000000000000000000 #
b10000000000000000000000000000000 )
b10000000000000000000000000000000 <
#110000
0$
#115000
1$
#116000
b0 Q
b0 P
#120000
0$
#125000
1$
#126000
b0 !
b0 .
b1111111111111111 -
b1111111111111111 7
b0 *
b0 :
b0 /
b10001 0
b0 +
b0 2
b0 =
b0 ,
b0 8
b0 9
b10000 ;
b0 %
b0 >
b0 #
b0 )
b0 <
b0 "
b0 (
b0 1
#130000
0$
#135000
1$
#136000
b10010001101000101011001111000 P
#140000
0$
#145000
1$
#146000
b10000 ;
b10010001101000101011001111000 "
b10010001101000101011001111000 (
b10010001101000101011001111000 1
#150000
0$
#155000
1$
#156000
b1 Q
b10000000000000000000000000000000 P
#160000
0$
#165000
1$
#166000
b1111111111111111111111111111111110000000000000000000000000000000 !
b1111111111111111111111111111111110000000000000000000000000000000 .
b11111111111111111111111111111111110000000000000000000000000000000 /
b10001 0
b1111111111111110 -
b1111111111111110 7
b110000000000000000000000000000000 ,
b110000000000000000000000000000000 8
b0 9
b10 +
b10 2
b10 =
b10000 ;
13
b1111111111111111111111111111111110000000000000000000000000000000 %
b10 >
b1 #
b1 )
b1 <
b10000000000000000000000000000000 "
b10000000000000000000000000000000 (
b10000000000000000000000000000000 1
#170000
0$
#175000
1$
#176000
b11111111111111111111111111111111 Q
b1111111111111111111111111111111 P
#180000
0$
#185000
1$
#186000
b1111111111111111111111111111111110000000000000000000000000000001 !
b1111111111111111111111111111111110000000000000000000000000000001 .
b1 *
b1 :
b11111111111111111111111111111111110000000000000000000000000000001 /
b10001 0
b111111111111111111111111111111111111111111111110 +
b111111111111111111111111111111111111111111111110 2
b111111111111111111111111111111111111111111111110 =
b1111111111111110 -
b1111111111111110 7
b110000000000000000000000000000000 ,
b110000000000000000000000000000000 8
b111 9
b10000 ;
03
b1111111111111111111111111111111110000000000000000000000000000001 %
b111111111111111111111111111111110 >
b11111111111111111111111111111111 #
b11111111111111111111111111111111 )
b11111111111111111111111111111111 <
b1111111111111111111111111111111 "
b1111111111111111111111111111111 (
b1111111111111111111111111111111 1
#190000
0$
#195000
1$
#196000
b1111111111111111111111111110011 Q
b11 P
#200000
0$
#205000
1$
#206000
b101111111111111111111111111011001 !
b101111111111111111111111111011001 .
b1111111111111010 -
b1111111111111010 7
b101 *
b101 :
b101111111111111111111111111011001 /
b10001 0
b11111111111111111111111111111111111111110001110 +
b11111111111111111111111111111111111111110001110 2
b11111111111111111111111111111111111111110001110 =
b110000000000000000000000000000000000000000000000000000000000000000000000000000000000000000000000000000000000000000000000000000000000000000000000000000000000000000000000000000000000000000000000000000000000000000000000000000000000000000000000000000000000000000000000000000000000000000000000000000000000000000000000000000000000000000000000000000000000000000000000000000000000000000000000000000000000000111111111111111111111111111111100000000000000000000000000000000011111111111111111111111111111111100 ,
b110000000000000000000000000000000000000000000000000000000000000000000000000000000000000000000000000000000000000000000000000000000000000000000000000000000000000000000000000000000000000000000000000000000000000000000000000000000000000000000000000000000000000000000000000000000000000000000000000000000000000000000000000000000000000000000000000000000000000000000000000000000000000000000000000000000000000111111111111111111111111111111100000000000000000000000000000000011111111111111111111111111111111100 8
b11 9
b10000 ;
b101111111111111111111111111011001 %
b11111111111111111111111111100110 >
b1111111111111111111111111110011 #
b1111111111111111111111111110011 )
b1111111111111111111111111110011 <
b11 "
b11 (
b11 1
#210000
0$
#215000
1$
#216000
b101 Q
b11111111111111111111111111111101 P
#220000
0$
#225000
1$
#226000
b1111111111111111111111111111111111111111111111111111111111110001 !
b1111111111111111111111111111111111111111111111111111111111110001 .
b0 *
b0 :
b11111111111111111111111111111111111111111111111111111111111110001 /
b10001 0
b10010 +
b10010 2
b10010 =
b1111111111111100 -
b1111111111111100 7
b111111111111111111111111111111101111111111111111111111111111111101 ,
b111111111111111111111111111111101111111111111111111111111111111101 8
b0 9
b10000 ;
13
b1111111111111111111111111111111111111111111111111111111111110001 %
b1010 >
b101 #
b101 )
b101 <
b11111111111111111111111111111101 "
b11111111111111111111111111111101 (
b11111111111111111111111111111101 1
#230000
0$
#235000
1$
#236000
b11000000100010010101111010000001 Q
b10010000101010011010100100100 P
b0 '
#240000
0$
#245000
1$
#246000
b1111101110000100011001101011110101010110011101101111111100100100 !
b1111101110000100011001101011110101010110011101101111111100100100 .
b1000101000011000 *
b1000101000011000 :
b11111101110000100011001101011110101010110011101101111111100100100 /
b10001 0
b110000000001100001100010010011111101100000000010 +
b110000000001100001100010010011111101100000000010 2
b110000000001100001100010010011111101100000000010 =
b111010111100111 -
b111010111100111 7
b111101101111010101100101011011011000000000000000000000000000000000000000000000000000000000000000000000010010000101010011010100100100111011011110101011001010110110111000010010000101010011010100100100111011011110101011001010110110111000010010000101010011010100100100000010010000101010011010100100100000100100001010100110101001001000000000000000000000000000000000000111101101111010101100101011011011111011011110101011001010110110111000000000000000000000000000000000000000000000000000000000000000000000010010000101010011010100100100 ,
b111101101111010101100101011011011000000000000000000000000000000000000000000000000000000000000000000000010010000101010011010100100100111011011110101011001010110110111000010010000101010011010100100100111011011110101011001010110110111000010010000101010011010100100100000010010000101010011010100100100000100100001010100110101001001000000000000000000000000000000000000111101101111010101100101011011011111011011110101011001010110110111000000000000000000000000000000000000000000000000000000000000000000000010010000101010011010100100100 8
b110 9
b10000 ;
03
b1111101110000100011001101011110101010110011101101111111100100100 %
b110000001000100101011110100000010 >
b11000000100010010101111010000001 #
b11000000100010010101111010000001 )
b11000000100010010101111010000001 <
b10010000101010011010100100100 "
b10010000101010011010100100100 (
b10010000101010011010100100100 1
#250000
0$
#255000
1$
#256000
b10110001111100000101011001100011 Q
b10000100100001001101011000001001 P
b1 '
#260000
0$
#265000
1$
#266000
b10010110100111000101001101000011000000101101011100101101111011 !
b10010110100111000101001101000011000000101101011100101101111011 .
b1100010000010101 *
b1100010000010101 :
b10010110100111000101001101000011000000101101011100101101111011 /
b10001 0
b101110000011111110000000010010011100011100001110 +
b101110000011111110000000010010011100011100001110 2
b101110000011111110000000010010011100011100001110 =
b1110111100010101 -
b1110111100010101 7
b1111011011110110010100111110110001111011011110110010100111110110000000000000000000000000000000000100001001000010011010110000010010000000000000000000000000000000000001111011011110110010100111110110000000000000000000000000000000000000000000000000000000000000000000110000100100001001101011000001001110000100100001001101011000001001100001001000010011010110000010010011110110111101100101001111101101100001001000010011010110000010010011110110111101100101001111101101110000100100001001101011000001001001111011011110110010100111110110 ,
b1111011011110110010100111110110001111011011110110010100111110110000000000000000000000000000000000100001001000010011010110000010010000000000000000000000000000000000001111011011110110010100111110110000000000000000000000000000000000000000000000000000000000000000000110000100100001001101011000001001110000100100001001101011000001001100001001000010011010110000010010011110110111101100101001111101101100001001000010011010110000010010011110110111101100101001111101101110000100100001001101011000001001001111011011110110010100111110110 8
b101 9
b10000 ;
13
b10010110100111000101001101000011000000101101011100101101111011 %
b101100011111000001010110011000110 >
b10110001111100000101011001100011 #
b10110001111100000101011001100011 )
b10110001111100000101011001100011 <
b10000100100001001101011000001001 "
b10000100100001001101011000001001 (
b10000100100001001101011000001001 1
#270000
0$
#275000
1$
#276000
b1000110110111111001100110001101 Q
b110101110010111101100001101 P
b10 '
#280000
0$
#285000
1$
#286000
b111011100100101110100000001001101000001101000101100101001 !
b111011100100101110100000001001101000001101000101100101001 .
b1100010101010 *
b1100010101010 :
b111011100100101110100000001001101000001101000101100101001 /
b10001 0
b10000011101110011111111100011100011100001110010 +
b10000011101110011111111100011100011100001110010 2
b10000011101110011111111100011100011100001110010 =
b1110011101010101 -
b1110011101010101 7
b110101110010111101100001101000000000000000000000000000000000000001101011100101111011000011010111111001010001101000010011110010111111001010001101000010011110010000001101011100101111011000011010000000000000000000000000000000000000000000000000000000000000000000111110010100011010000100111100101000001101011100101111011000011010111110010100011010000100111100101000001101011100101111011000011010111110010100011010000100111100101000000110101110010111101100001101111111001010001101000010011110010000000110101110010111101100001101 ,
b110101110010111101100001101000000000000000000000000000000000000001101011100101111011000011010111111001010001101000010011110010111111001010001101000010011110010000001101011100101111011000011010000000000000000000000000000000000000000000000000000000000000000000111110010100011010000100111100101000001101011100101111011000011010111110010100011010000100111100101000001101011100101111011000011010111110010100011010000100111100101000000110101110010111101100001101111111001010001101000010011110010000000110101110010111101100001101 8
b10 9
b10000 ;
03
b111011100100101110100000001001101000001101000101100101001 %
b10001101101111110011001100011010 >
b1000110110111111001100110001101 #
b1000110110111111001100110001101 )
b1000110110111111001100110001101 <
b110101110010111101100001101 "
b110101110010111101100001101 (
b110101110010111101100001101 1
#290000
0$
#295000
1$
#296000
b10001001001101110101001000010010 Q
b10110010110000101000010001100101 P
b11 '
#300000
0$
#305000
1$
#306000
b10001111010110111000110111110001011110110010001010100100011010 !
b10001111010110111000110111110001011110110010001010100100011010 .
b1010010100010001 *
b1010010100010001 :
b10001111010110111000110111110001011110110010001010100100011010 /
b10001 0
b100001100010001110011110010010001100000010001100 +
b100001100010001110011110010010001100000010001100 2
b100001100010001110011110010010001100000010001100 =
b100 9
b1010010100011001 -
b1010010100011001 7
b10011010011110101111011100110101110110010110000101000010001100101010011010011110101111011100110101110110010110000101000010001100101110110010110000101000010001100101001001101001111010111101110011010101100101100001010000100011001010001001101001111010111101110011010110110010110000101000010001100101110110010110000101000010001100101110110010110000101000010001100101010011010011110101111011100110101000000000000000000000000000000000110110010110000101000010001100101110110010110000101000010001100101010011010011110101111011100110101 ,
b10011010011110101111011100110101110110010110000101000010001100101010011010011110101111011100110101110110010110000101000010001100101110110010110000101000010001100101001001101001111010111101110011010101100101100001010000100011001010001001101001111010111101110011010110110010110000101000010001100101110110010110000101000010001100101110110010110000101000010001100101010011010011110101111011100110101000000000000000000000000000000000110110010110000101000010001100101110110010110000101000010001100101010011010011110101111011100110101 8
b10000 ;
13
b10001111010110111000110111110001011110110010001010100100011010 %
b100010010011011101010010000100100 >
b10001001001101110101001000010010 #
b10001001001101110101001000010010 )
b10001001001101110101001000010010 <
b10110010110000101000010001100101 "
b10110010110000101000010001100101 (
b10110010110000101000010001100101 1
#310000
0$
#315000
1$
#316000
b110110101111100110100001101 Q
b111100111110001100000001 P
b100 '
#320000
0$
#325000
1$
#326000
b110100001001110100100000101000000010101010000001101 !
b110100001001110100100000101000000010101010000001101 .
b1100010100010 *
b1100010100010 :
b110100001001110100100000101000000010101010000001101 /
b10001 0
b11101110010011111110001110010000001110010 +
b11101110010011111110001110010000001110010 2
b11101110010011111110001110010000001110010 =
b0 9
b1110011101011101 -
b1110011101011101 7
b1111001111100011000000010111111111000011000001110011111110111111111000011000001110011111110000000000111100111110001100000001000000001111001111100011000000010000000000000000000000000000000000111111111000011000001110011111110000000000111100111110001100000001111111111000011000001110011111110000000000111100111110001100000001000000000000000000000000000000000000000000111100111110001100000001111111111000011000001110011111110000000000111100111110001100000001 ,
b1111001111100011000000010111111111000011000001110011111110111111111000011000001110011111110000000000111100111110001100000001000000001111001111100011000000010000000000000000000000000000000000111111111000011000001110011111110000000000111100111110001100000001111111111000011000001110011111110000000000111100111110001100000001000000000000000000000000000000000000000000111100111110001100000001111111111000011000001110011111110000000000111100111110001100000001 8
b10000 ;
03
b110100001001110100100000101000000010101010000001101 %
b1101101011111001101000011010 >
b110110101111100110100001101 #
b110110101111100110100001101 )
b110110101111100110100001101 <
b111100111110001100000001 "
b111100111110001100000001 (
b111100111110001100000001 1
#330000
0$
#335000
1$
#336000
b11110100011011100110100111101 Q
b111011001000111111000101110110 P
b101 '
#340000
0$
#345000
1$
